fanos/__init__.py
fanos/fanos_chain_optimizer.py
fanos/fanos_optimizer.py
fanos_optimizer-0.2.0.dist-info/METADATA
fanos_optimizer-0.2.0.dist-info/WHEEL
fanos_optimizer-0.2.0.dist-info/licenses/LICENSE
fanos_optimizer-0.2.0.dist-info/RECORD
