Metadata-Version: 2.4
Name: fanos-optimizer
Version: 0.2.0
Summary: FANoS: Friction-Adaptive Nosé–Hoover Symplectic momentum optimizer for PyTorch.
Project-URL: Homepage, https://github.com/nalin-dhiman/fanos
Project-URL: Repository, https://github.com/nalin-dhiman/fanos
Project-URL: Documentation, https://github.com/nalin-dhiman/fanos#readme
Project-URL: Bug Tracker, https://github.com/nalin-dhiman/fanos/issues
Author: Nalin Dhiman
License: MIT License
License-File: LICENSE
Keywords: momentum,nose-hoover,optimizer,pytorch,symplectic,thermostat
Classifier: Development Status :: 3 - Alpha
Classifier: Intended Audience :: Science/Research
Classifier: License :: OSI Approved :: MIT License
Classifier: Programming Language :: Python :: 3
Classifier: Topic :: Scientific/Engineering :: Artificial Intelligence
Requires-Python: >=3.9
Requires-Dist: torch>=2.0
